odoo10_addon_mail_tracking_mass_mailing-10.0.1.0.1-py2.7-nspkg.pth
odoo/addons/mail_tracking_mass_mailing/README.rst
odoo/addons/mail_tracking_mass_mailing/__init__.py
odoo/addons/mail_tracking_mass_mailing/__manifest__.py
odoo/addons/mail_tracking_mass_mailing/hooks.py
odoo/addons/mail_tracking_mass_mailing/i18n/ca.po
odoo/addons/mail_tracking_mass_mailing/i18n/da.po
odoo/addons/mail_tracking_mass_mailing/i18n/de.po
odoo/addons/mail_tracking_mass_mailing/i18n/el_GR.po
odoo/addons/mail_tracking_mass_mailing/i18n/es.po
odoo/addons/mail_tracking_mass_mailing/i18n/es_CO.po
odoo/addons/mail_tracking_mass_mailing/i18n/eu.po
odoo/addons/mail_tracking_mass_mailing/i18n/fi.po
odoo/addons/mail_tracking_mass_mailing/i18n/fr.po
odoo/addons/mail_tracking_mass_mailing/i18n/gl.po
odoo/addons/mail_tracking_mass_mailing/i18n/hr.po
odoo/addons/mail_tracking_mass_mailing/i18n/hr_HR.po
odoo/addons/mail_tracking_mass_mailing/i18n/it.po
odoo/addons/mail_tracking_mass_mailing/i18n/nb_NO.po
odoo/addons/mail_tracking_mass_mailing/i18n/nl.po
odoo/addons/mail_tracking_mass_mailing/i18n/nl_NL.po
odoo/addons/mail_tracking_mass_mailing/i18n/pl.po
odoo/addons/mail_tracking_mass_mailing/i18n/pt.po
odoo/addons/mail_tracking_mass_mailing/i18n/pt_BR.po
odoo/addons/mail_tracking_mass_mailing/i18n/ro.po
odoo/addons/mail_tracking_mass_mailing/i18n/ru.po
odoo/addons/mail_tracking_mass_mailing/i18n/sl.po
odoo/addons/mail_tracking_mass_mailing/i18n/tr.po
odoo/addons/mail_tracking_mass_mailing/models/__init__.py
odoo/addons/mail_tracking_mass_mailing/models/mail_mail.py
odoo/addons/mail_tracking_mass_mailing/models/mail_mail_statistics.py
odoo/addons/mail_tracking_mass_mailing/models/mail_mass_mailing_contact.py
odoo/addons/mail_tracking_mass_mailing/models/mail_tracking_email.py
odoo/addons/mail_tracking_mass_mailing/models/mail_tracking_event.py
odoo/addons/mail_tracking_mass_mailing/static/description/icon.png
odoo/addons/mail_tracking_mass_mailing/tests/__init__.py
odoo10_addon_mail_tracking_mass_mailing-10.0.1.0.1.dist-info/DESCRIPTION.rst
odoo10_addon_mail_tracking_mass_mailing-10.0.1.0.1.dist-info/METADATA
odoo10_addon_mail_tracking_mass_mailing-10.0.1.0.1.dist-info/RECORD
odoo10_addon_mail_tracking_mass_mailing-10.0.1.0.1.dist-info/WHEEL
odoo10_addon_mail_tracking_mass_mailing-10.0.1.0.1.dist-info/metadata.json
odoo10_addon_mail_tracking_mass_mailing-10.0.1.0.1.dist-info/namespace_packages.txt
odoo10_addon_mail_tracking_mass_mailing-10.0.1.0.1.dist-info/top_level.txt
